<?xml version='1.0' encoding='UTF-8'?>
<annotation>
  <folder>annotations</folder>
  <filename>n003-2018-07-12-15-40-35+0800__CAM_BACK__1531383596387543.jpg</filename>
  <path>/content/sample_data/images/n003-2018-07-12-15-40-35+0800__CAM_BACK__1531383596387543.jpg</path>
  <directory>/content/sample_data/images/n003-2018-07-12-15-40-35+0800__CAM_BACK__1531383596387543.jpg</directory>
  <size>
    <width>1600</width>
    <height>900</height>
    <depth>3</depth>
  </size>
  <object>
    <name>vehicle.car</name>
    <pose>Unspecified</pose>
    <truncated>0</truncated>
    <difficult>0</difficult>
    <bndbox>
      <xmin>640</xmin>
      <ymin>424</ymin>
      <xmax>704</xmax>
      <ymax>467</ymax>
    </bndbox>
  </object>
  <object>
    <name>vehicle.motorcycle</name>
    <pose>Unspecified</pose>
    <truncated>0</truncated>
    <difficult>0</difficult>
    <bndbox>
      <xmin>752</xmin>
      <ymin>414</ymin>
      <xmax>784</xmax>
      <ymax>478</ymax>
    </bndbox>
  </object>
  <object>
    <name>human.pedestrian.adult</name>
    <pose>Unspecified</pose>
    <truncated>0</truncated>
    <difficult>0</difficult>
    <bndbox>
      <xmin>971</xmin>
      <ymin>400</ymin>
      <xmax>990</xmax>
      <ymax>426</ymax>
    </bndbox>
  </object>
  <object>
    <name>vehicle.car</name>
    <pose>Unspecified</pose>
    <truncated>0</truncated>
    <difficult>0</difficult>
    <bndbox>
      <xmin>777</xmin>
      <ymin>411</ymin>
      <xmax>860</xmax>
      <ymax>497</ymax>
    </bndbox>
  </object>
</annotation>
