<?xml version='1.0' encoding='UTF-8'?>
<annotation>
  <folder>annotations</folder>
  <filename>n003-2018-01-05-16-07-19+0800__CAM_FRONT__1515139879985642.jpg</filename>
  <path>C:/Users/mgavilan/Downloads/datasets/test/images\n003-2018-01-05-16-07-19+0800__CAM_FRONT__1515139879985642.jpg</path>
  <directory>C:/Users/mgavilan/Downloads/datasets/test/images\n003-2018-01-05-16-07-19+0800__CAM_FRONT__1515139879985642.jpg</directory>
  <size>
    <width>1600</width>
    <height>900</height>
    <depth>3</depth>
  </size>
  <object>
    <name>human.pedestrian.adult-pedestrian.standing</name>
    <pose>Unspecified</pose>
    <truncated>0</truncated>
    <difficult>0</difficult>
    <bndbox>
      <xmin>280</xmin>
      <ymin>417</ymin>
      <xmax>412</xmax>
      <ymax>613</ymax>
    </bndbox>
  </object>
  <object>
    <name>human.pedestrian.adult-pedestrian.moving</name>
    <pose>Unspecified</pose>
    <truncated>0</truncated>
    <difficult>0</difficult>
    <bndbox>
      <xmin>929</xmin>
      <ymin>456</ymin>
      <xmax>951</xmax>
      <ymax>519</ymax>
    </bndbox>
  </object>
  <object>
    <name>human.pedestrian.adult-pedestrian.moving</name>
    <pose>Unspecified</pose>
    <truncated>0</truncated>
    <difficult>0</difficult>
    <bndbox>
      <xmin>1174</xmin>
      <ymin>451</ymin>
      <xmax>1212</xmax>
      <ymax>535</ymax>
    </bndbox>
  </object>
</annotation>
